[
 {
   "Well pad #": 1,
   "Lat": 43.21466,
   "Lon": -105.805,
   "Wellhead": "Andromeda, Aries 447, 434",
   "Q_med": "0.657, 2.19",
   "Q_low": "0.234, 0.362",
   "Q_high": "2.658, 3.233",
   "Abnormal": "No, No",
   "Detections": "4, 8"
 },
 {
   "Well pad #": 2,
   "Lat": 43.21453,
   "Lon": -105.811,
   "Wellhead": "Aries 409",
   "Q_med": "0.73, 0.5",
   "Q_low": "N/A, 0.313",
   "Q_high": "N/A, 0.598",
   "Abnormal": "No, No",
   "Detections": "1, 4"
 },
 {
   "Well pad #": 3,
   "Lat": 43.1861,
   "Lon": -105.784,
   "Wellhead": "Centaur",
   "Q_med": "0.286, 0.173",
   "Q_low": "0.023, 0.09",
   "Q_high": "3.264, 0.256",
   "Abnormal": "Yes, No",
   "Detections": "3, 2"
 },
 {
   "Well pad #": 4,
   "Lat": 43.1864,
   "Lon": -105.725,
   "Wellhead": "Dorado 408, 440, 344",
   "Q_med": "0.018, 0.054",
   "Q_low": "0.005, 0.026",
   "Q_high": "0.103, 0.459",
   "Abnormal": "No, Yes",
   "Detections": "13, 11"
 },
 {
   "Well pad #": 5,
   "Lat": 43.18476,
   "Lon": -105.829,
   "Wellhead": "Eros 419",
   "Q_med": "0.059, 0.949",
   "Q_low": "N/A, 0.008",
   "Q_high": "N/A, 1.891",
   "Abnormal": "No, No",
   "Detections": "1, 2"
 },
 {
   "Well pad #": 6,
   "Lat": 43.20439,
   "Lon": -105.754,
   "Wellhead": "Ford Federal 23-4",
   "Q_med": "0.312, 0.104",
   "Q_low": "N/A, 0.034",
   "Q_high": "N/A, 0.681",
   "Abnormal": "No, No",
   "Detections": "1, 3"
 },
 {
   "Well pad #": 7,
   "Lat": 43.18664,
   "Lon": -105.713,
   "Wellhead": "Gemini 426, 412",
   "Q_med": "0.095, 0.605",
   "Q_low": "0.024, 0.311",
   "Q_high": "1.271, 0.72",
   "Abnormal": "Yes, No",
   "Detections": "5, 3"
 },
 {
   "Well pad #": 8,
   "Lat": 43.17702,
   "Lon": -105.816,
   "Wellhead": "Grassroots SWD",
   "Q_med": "0.071, 0.382",
   "Q_low": "N/A, 0.264",
   "Q_high": "N/A, 1.27",
   "Abnormal": "No, No",
   "Detections": "1, 4"
 },
 {
   "Well pad #": 9,
   "Lat": 43.15261,
   "Lon": -105.814,
   "Wellhead": "Hart 1-25X",
   "Q_med": "0.664, N/A",
   "Q_low": "0.432, N/A",
   "Q_high": "0.892, N/A",
   "Abnormal": "No, ",
   "Detections": "3, 0"
 },
 {
   "Well pad #": 10,
   "Lat": 43.1908,
   "Lon": -105.796,
   "Wellhead": "Henry 12-7",
   "Q_med": "3.415, 1.002",
   "Q_low": "2.536, 0.666",
   "Q_high": "4.202, 1.84",
   "Abnormal": "No, No",
   "Detections": "3, 7"
 },
 {
   "Well pad #": 11,
   "Lat": 43.16963,
   "Lon": -105.867,
   "Wellhead": "Icarus 434",
   "Q_med": "0.224, 0.612",
   "Q_low": "N/A, 0.175",
   "Q_high": "N/A, 4.479",
   "Abnormal": "No, Yes",
   "Detections": "1, 5"
 },
 {
   "Well pad #": 12,
   "Lat": 43.18584,
   "Lon": -105.848,
   "Wellhead": "Juno 426, Diana 419",
   "Q_med": "0.343, 1.877",
   "Q_low": "0.118, 0.104",
   "Q_high": "0.91, 3.65",
   "Abnormal": "Yes, No",
   "Detections": "12, 2"
 },
 {
   "Well pad #": 13,
   "Lat": 43.18476,
   "Lon": -105.776,
   "Wellhead": "Leda 409",
   "Q_med": "0.128, 0.33",
   "Q_low": "N/A, 0.253",
   "Q_high": "N/A, 0.389",
   "Abnormal": "No, No",
   "Detections": "1, 3"
 },
 {
   "Well pad #": 14,
   "Lat": 43.18458,
   "Lon": -105.787,
   "Wellhead": "Leo 434",
   "Q_med": "1.407, 0.243",
   "Q_low": "0.861, 0.212",
   "Q_high": "22.233, 0.602",
   "Abnormal": "Yes, No",
   "Detections": "3, 3"
 },
 {
   "Well pad #": 15,
   "Lat": 43.18449,
   "Lon": -105.77,
   "Wellhead": "Lynx 409, 330",
   "Q_med": "0.098, 0.23",
   "Q_low": "0.006, 0.128",
   "Q_high": "0.693, 2.804",
   "Abnormal": "Yes, Yes",
   "Detections": "5, 5"
 },
 {
   "Well pad #": 16,
   "Lat": 43.18483,
   "Lon": -105.81,
   "Wellhead": "Orion 409",
   "Q_med": "0.131, 0.35",
   "Q_low": "0.112, 0.274",
   "Q_high": "0.435, 1.496",
   "Abnormal": "No, No",
   "Detections": "5, 4"
 },
 {
   "Well pad #": 17,
   "Lat": 43.14449,
   "Lon": -105.864,
   "Wellhead": "Pandora 440",
   "Q_med": "0.27, 0.066",
   "Q_low": "0.228, 0.06",
   "Q_high": "0.311, 0.778",
   "Abnormal": "No, Yes",
   "Detections": "2, 7"
 },
 {
   "Well pad #": 18,
   "Lat": 43.12866,
   "Lon": -105.803,
   "Wellhead": "Phoenix 244, 447",
   "Q_med": "0.605, 0.216",
   "Q_low": "0.325, 0.191",
   "Q_high": "0.884, 0.24",
   "Abnormal": "No, No",
   "Detections": "2, 2"
 },
 {
   "Well pad #": 19,
   "Lat": 43.1288,
   "Lon": -105.792,
   "Wellhead": "Scorpio 419",
   "Q_med": "0.175, 0.605",
   "Q_low": "0.138, 0.213",
   "Q_high": "0.67, 1.57",
   "Abnormal": "No, No",
   "Detections": "9, 3"
 },
 {
   "Well pad #": 20,
   "Lat": 43.12739,
   "Lon": -105.784,
   "Wellhead": "Scorpio 441",
   "Q_med": "0.147, N/A",
   "Q_low": "N/A, N/A",
   "Q_high": "N/A, N/A",
   "Abnormal": "No, ",
   "Detections": "1, 0"
 },
 {
   "Well pad #": 21,
   "Lat": 43.12792,
   "Lon": -105.776,
   "Wellhead": "Taurus 406",
   "Q_med": "3.691, 0.142",
   "Q_low": "1.087, 0.05",
   "Q_high": "6.113, 0.46",
   "Abnormal": "No, No",
   "Detections": "4, 8"
 },
 {
   "Well pad #": 22,
   "Lat": 43.1842,
   "Lon": -105.719,
   "Wellhead": "Ursa Minor 400D",
   "Q_med": "4.054, 0.192",
   "Q_low": "0.207, 0.064",
   "Q_high": "7.901, 0.49",
   "Abnormal": "No, No",
   "Detections": "2, 3"
 },
 {
   "Well pad #": 23,
   "Lat": 43.1297,
   "Lon": -105.753,
   "Wellhead": "Virgo 408",
   "Q_med": "0.194, 0.16",
   "Q_low": "0.044, N/A",
   "Q_high": "0.564, N/A",
   "Abnormal": "No, No",
   "Detections": "3, 1"
 },
 {
   "Well pad #": 24,
   "Lat": 43.12872,
   "Lon": -105.744,
   "Wellhead": "Virgo 437",
   "Q_med": "0.426, 0.45",
   "Q_low": "0.152, 0.269",
   "Q_high": "5.187, 0.705",
   "Abnormal": "Yes, No",
   "Detections": "4, 6"
 }
]